redash_python/__init__.py
redash_python/redash.py
redash_python/services/__init__.py
redash_python/services/alerts.py
redash_python/services/base.py
redash_python/services/dashboards.py
redash_python/services/data_sources.py
redash_python/services/destinations.py
redash_python/services/groups.py
redash_python/services/mixins.py
redash_python/services/queries.py
redash_python/services/query_snippets.py
redash_python/services/users.py
redash_python/services/widgets.py
redash_python-0.3.27.dist-info/LICENSE
redash_python-0.3.27.dist-info/METADATA
redash_python-0.3.27.dist-info/WHEEL
redash_python-0.3.27.dist-info/top_level.txt
redash_python-0.3.27.dist-info/RECORD
