Metadata-Version: 2.1
Name: redash-python
Version: 0.3.27
Summary: A more complete Python client for the Redash API
Author-email: blacksuan19 <py@blacksuan19.dev>
License: BSD-2-Clause
Project-URL: Homepage, https://redash.blacksuan19.dev/
Project-URL: Documentation, https://redash.blacksuan19.dev/
Project-URL: Repository, https://github.com/blacksuan19/redash-python/
Project-URL: Issues, https://github.com/blacksuan19/redash-python/issues
Keywords: redash
Classifier: License :: OSI Approved :: BSD License
Classifier: Programming Language :: Python
Classifier: Programming Language :: Python :: 3
Requires-Python: >=3.7
License-File: LICENSE
Requires-Dist: requests
Provides-Extra: dev
Requires-Dist: black ; extra == 'dev'
Requires-Dist: bumpver ; extra == 'dev'
Requires-Dist: pip-tools ; extra == 'dev'
Requires-Dist: wheel ; extra == 'dev'
Requires-Dist: requests ; extra == 'dev'
